odoo8_addon_account_invoice_sequential_dates-8.0.1.0.0.99.dev7-py2.7-nspkg.pth
odoo8_addon_account_invoice_sequential_dates-8.0.1.0.0.99.dev7.dist-info/METADATA
odoo8_addon_account_invoice_sequential_dates-8.0.1.0.0.99.dev7.dist-info/RECORD
odoo8_addon_account_invoice_sequential_dates-8.0.1.0.0.99.dev7.dist-info/WHEEL
odoo8_addon_account_invoice_sequential_dates-8.0.1.0.0.99.dev7.dist-info/namespace_packages.txt
odoo8_addon_account_invoice_sequential_dates-8.0.1.0.0.99.dev7.dist-info/top_level.txt
odoo_addons/account_invoice_sequential_dates/README.rst
odoo_addons/account_invoice_sequential_dates/__init__.py
odoo_addons/account_invoice_sequential_dates/__openerp__.py
odoo_addons/account_invoice_sequential_dates/invoice.py
odoo_addons/account_invoice_sequential_dates/i18n/account_invoice_sequential_dates.pot
odoo_addons/account_invoice_sequential_dates/i18n/it.po
odoo_addons/account_invoice_sequential_dates/i18n/sl.po
odoo_addons/account_invoice_sequential_dates/static/description/icon.png
